SikuliPlusLibrary/__init__.py
SikuliPlusLibrary/config.py
SikuliPlusLibrary/helpers.py
SikuliPlusLibrary/main.py
SikuliPlusLibrary/signature_utils.py
SikuliPlusLibrary/mixins/__init__.py
SikuliPlusLibrary/mixins/context_managers.py
SikuliPlusLibrary/modules/__init__.py
SikuliPlusLibrary/modules/vision.py
robotframework_sikulipluslibrary-0.1.4.dist-info/METADATA
robotframework_sikulipluslibrary-0.1.4.dist-info/WHEEL
robotframework_sikulipluslibrary-0.1.4.dist-info/licenses/LICENSE
robotframework_sikulipluslibrary-0.1.4.dist-info/RECORD
