Metadata-Version: 2.4
Name: robotframework-SikuliPlusLibrary
Version: 0.1.4
Summary: A wrapper for robotframework-SikuliLibrary to be used with Robot Framework
Project-URL: Homepage, https://github.com/LeonardoSextare/robotframework-SikuliPlusLibrary
Project-URL: Issues, https://github.com/LeonardoSextare/robotframework-SikuliPlusLibrary/issues
Author-email: Leonardo Sextare <leonardosextare@gmail.com>
License-File: LICENSE
Classifier: Framework :: Robot Framework :: Library
Classifier: License :: OSI Approved :: Apache Software License
Classifier: Programming Language :: Python :: 3
Requires-Python: >=3.13
Requires-Dist: robotframework-sikulilibrary<2.0.5,>=2.0.3
Requires-Dist: robotframework>=7.0.0
